graph_dynamo/Markov.py
graph_dynamo/__init__.py
graph_dynamo/graph_calculus.py
graph_dynamo/tangent_space.py
graph_dynamo-0.1.1.dist-info/METADATA
graph_dynamo-0.1.1.dist-info/WHEEL
graph_dynamo-0.1.1.dist-info/top_level.txt
graph_dynamo-0.1.1.dist-info/RECORD
