Metadata-Version: 2.1
Name: graph-dynamo
Version: 0.1.1
Summary: A Python library for working with graphs in Amazon DynamoDB
Home-page: https://github.com/xing-lab-pitt/graph-dynamo/
Author: {Yan Zhang, Xiaojie Qiu, Ke Ni, Jonathan Weissman, Ivet Bahar, Jianhua Xing
Author-email: xing1@pitt.edu
Classifier: Programming Language :: Python :: 3
Classifier: License :: OSI Approved :: MIT License
Classifier: Operating System :: OS Independent
Requires-Python: >=3.6
Requires-Dist: typing-extensions >=3.10.0.0
Provides-Extra: dev
Requires-Dist: pytest >=6.2.4 ; extra == 'dev'
